README.md
setup.py
em_parser/__init__.py
em_parser/airline_logic.py
em_parser/airport_codes.json
em_parser/airports_graph.py
em_parser/cache.json
em_parser/clean_functions.py
em_parser/em_parser.py
em_parser/oldcopanames.py
em_parser/olduonames.py
em_parser/regexes.py
em_parser/upsert.json
em_parser/version.txt
em_parser.egg-info/PKG-INFO
em_parser.egg-info/SOURCES.txt
em_parser.egg-info/dependency_links.txt
em_parser.egg-info/requires.txt
em_parser.egg-info/top_level.txt
tests/__init__.py
tests/test_campaign_types.py
tests/test_parse.py
tests/test_kuwait/__init__.py
tests/test_kuwait/test_parser_kuwait.py
tests/test_with_hipothesis/__init__.py
tests/test_with_hipothesis/test_UO.py