Metadata-Version: 1.1
Name: em-parser
Version: 4.4.6
Summary: Parses Campaign and Adgroup names
Home-page: https://github.com/EveryMundo/CampaignAdgroupParser
Author: EveryMundo
Author-email: services@everymundo.com
License: UNKNOWN
Keywords: EveryMundo Parser
Platform: UNKNOWN
Classifier: Development Status :: 4 - Beta
Classifier: Intended Audience :: Developers
Classifier: Topic :: Software Development
Classifier: Programming Language :: Python :: 3
Classifier: Programming Language :: Python :: 3.3
Classifier: Programming Language :: Python :: 3.4
Classifier: Programming Language :: Python :: 3.5
Classifier: Programming Language :: Python :: 3.6
Classifier: Programming Language :: Python :: 3.7
Classifier: Programming Language :: Python :: 3.8
